gcoinrpc/__init__.py
gcoinrpc/config.py
gcoinrpc/connection.py
gcoinrpc/data.py
gcoinrpc/exceptions.py
gcoinrpc/proxy.py
gcoinrpc/util.py
pallium_rpc-0.4.1.dist-info/DESCRIPTION.rst
pallium_rpc-0.4.1.dist-info/METADATA
pallium_rpc-0.4.1.dist-info/RECORD
pallium_rpc-0.4.1.dist-info/WHEEL
pallium_rpc-0.4.1.dist-info/metadata.json
pallium_rpc-0.4.1.dist-info/top_level.txt
